pyfooda/VERSION
pyfooda/__init__.py
pyfooda/api.py
pyfooda/categories.py
pyfooda/cluster.py
pyfooda/myplot.py
pyfooda/nutrients_drv.py
pyfooda/preprocess_pandas.py
pyfooda/data/fooddata.csv
pyfooda/data/nutrients.csv
pyfooda-0.1.8.dist-info/METADATA
pyfooda-0.1.8.dist-info/WHEEL
pyfooda-0.1.8.dist-info/top_level.txt
pyfooda-0.1.8.dist-info/RECORD
